sgn_arrakis/__init__.py
sgn_arrakis/__main__.py
sgn_arrakis/_version.py
sgn_arrakis/sink.py
sgn_arrakis/source.py
sgn_arrakis/tests/conftest.py
sgn_arrakis/tests/test_data.py
sgn_arrakis/tests/test_source.py
sgn_arrakis-0.3.0.dist-info/METADATA
sgn_arrakis-0.3.0.dist-info/WHEEL
sgn_arrakis-0.3.0.dist-info/entry_points.txt
sgn_arrakis-0.3.0.dist-info/licenses/LICENSE
sgn_arrakis-0.3.0.dist-info/RECORD
