Metadata-Version: 2.4
Name: sgn-arrakis
Version: 0.3.0
Summary: Arrakis interfaces for sgn-ts
Project-URL: Homepage, https://git.ligo.org/ngdd/sgn_arrakis
Project-URL: Repository, https://git.ligo.org/ngdd/sgn_arrakis.git
Project-URL: Issues, https://git.ligo.org/ngdd/sgn_arrakis/issues
Author-email: Jameson Graef Rollins <jameson.rollins@ligo.org>
License-Expression: LGPL-3.0-or-later
License-File: LICENSE
Requires-Python: >=3.10
Requires-Dist: arrakis>=0.4.1
Requires-Dist: sgn-ts>=0.4
Requires-Dist: sgn>=0.4
Provides-Extra: dev
Requires-Dist: arrakis-server; (python_version >= '3.11') and extra == 'dev'
Requires-Dist: markdown-callouts>=0.2; extra == 'dev'
Requires-Dist: markdown-exec>=0.5; extra == 'dev'
Requires-Dist: mkdocs-coverage>=0.2; extra == 'dev'
Requires-Dist: mkdocs-gen-files>=0.3; extra == 'dev'
Requires-Dist: mkdocs-literate-nav>=0.4; extra == 'dev'
Requires-Dist: mkdocs-material-igwn; extra == 'dev'
Requires-Dist: mkdocs-section-index>=0.3; extra == 'dev'
Requires-Dist: mkdocs>=1.3; extra == 'dev'
Requires-Dist: mkdocstrings[python]; extra == 'dev'
Requires-Dist: mypy; extra == 'dev'
Requires-Dist: mypy-extensions; extra == 'dev'
Requires-Dist: pip; extra == 'dev'
Requires-Dist: pytest; extra == 'dev'
Requires-Dist: pytest-cov; extra == 'dev'
Requires-Dist: ruff; extra == 'dev'
Requires-Dist: toml>=0.10; extra == 'dev'
Provides-Extra: docs
Requires-Dist: markdown-callouts>=0.2; extra == 'docs'
Requires-Dist: markdown-exec>=0.5; extra == 'docs'
Requires-Dist: mkdocs-coverage>=0.2; extra == 'docs'
Requires-Dist: mkdocs-gen-files>=0.3; extra == 'docs'
Requires-Dist: mkdocs-literate-nav>=0.4; extra == 'docs'
Requires-Dist: mkdocs-material-igwn; extra == 'docs'
Requires-Dist: mkdocs-section-index>=0.3; extra == 'docs'
Requires-Dist: mkdocs>=1.3; extra == 'docs'
Requires-Dist: mkdocstrings[python]; extra == 'docs'
Requires-Dist: toml>=0.10; extra == 'docs'
Provides-Extra: lint
Requires-Dist: mypy; extra == 'lint'
Requires-Dist: mypy-extensions; extra == 'lint'
Requires-Dist: pip; extra == 'lint'
Requires-Dist: ruff; extra == 'lint'
Provides-Extra: publish
Requires-Dist: arrakis[publish]; extra == 'publish'
Provides-Extra: test
Requires-Dist: arrakis-server; (python_version >= '3.11') and extra == 'test'
Requires-Dist: pytest; extra == 'test'
Requires-Dist: pytest-cov; extra == 'test'
